my_package/__init__.py
my_package/evaluation.py
my_package/evaluation_upscaling.py
my_package/fix_prediction.py
my_package/gois_inference.py
my_package/inference.py
my_package/preprocessing.py
my_package/data_processing/__init__.py
my_package/data_processing/image_loader.py
my_package/models/__init__.py
my_package/models/model_utils.py
gois1-0.1.dist-info/LICENSE
gois1-0.1.dist-info/METADATA
gois1-0.1.dist-info/WHEEL
gois1-0.1.dist-info/entry_points.txt
gois1-0.1.dist-info/top_level.txt
gois1-0.1.dist-info/RECORD
