Metadata-Version: 2.1
Name: gois1
Version: 0.1
Summary: A package for GOIS-based inference, evaluation, and preprocessing
Home-page: https://github.com/MMUZAMMUL/GOIS
Author: MUHAMMAD MUZAMMUL
Author-email: munagreat123@gmail.com
Classifier: Programming Language :: Python :: 3
Classifier: License :: OSI Approved :: MIT License
Classifier: Operating System :: OS Independent
Requires-Python: >=3.6
License-File: LICENSE
Requires-Dist: ultralytics>=8.0.0
Requires-Dist: gdown>=4.5.1
Requires-Dist: pycocotools>=2.0.6
Requires-Dist: numpy>=1.21.6
Requires-Dist: Pillow>=9.0.1
Requires-Dist: torch>=1.10.0
